{"congress": "113", "bill_id": "hr3979-113", "num_results": 20, "offset": 0, "amendments": [{"amendment_number": "S.AMDT.4032", "slug": "samdt4032", "sponsor_title": "Sen.", "sponsor": "Tom Coburn", "sponsor_id": "C000560", "sponsor_uri": "https://api.propublica.org/congress/v1/members/C000560.json", "sponsor_party": "R", "sponsor_state": "OK", "introduced_date": "2014-12-10", "title": "", "congressdotgov_url": "https://www.congress.gov/amendment/113th-congress/senate-amendment/4032/text", "latest_major_action_date": "2014-12-10", "latest_major_action": "Senate amendment submitted"}, {"amendment_number": "S.AMDT.4033", "slug": "samdt4033", "sponsor_title": "Sen.", "sponsor": "Tom Coburn", "sponsor_id": "C000560", "sponsor_uri": "https://api.propublica.org/congress/v1/members/C000560.json", "sponsor_party": "R", "sponsor_state": "OK", "introduced_date": "2014-12-10", "title": "", "congressdotgov_url": "https://www.congress.gov/amendment/113th-congress/senate-amendment/4033/text", "latest_major_action_date": "2014-12-10", "latest_major_action": "Senate amendment submitted"}, {"amendment_number": "S.AMDT.4034", "slug": "samdt4034", "sponsor_title": "Sen.", "sponsor": "Tom Coburn", "sponsor_id": "C000560", "sponsor_uri": "https://api.propublica.org/congress/v1/members/C000560.json", "sponsor_party": "R", "sponsor_state": "OK", "introduced_date": "2014-12-10", "title": "", "congressdotgov_url": "https://www.congress.gov/amendment/113th-congress/senate-amendment/4034/text", "latest_major_action_date": "2014-12-10", "latest_major_action": "Senate amendment submitted"}, {"amendment_number": "S.AMDT.4035", "slug": "samdt4035", "sponsor_title": "Sen.", "sponsor": "Tom Coburn", "sponsor_id": "C000560", "sponsor_uri": "https://api.propublica.org/congress/v1/members/C000560.json", "sponsor_party": "R", "sponsor_state": "OK", "introduced_date": "2014-12-10", "title": "", "congressdotgov_url": "https://www.congress.gov/amendment/113th-congress/senate-amendment/4035/text", "latest_major_action_date": "2014-12-10", "latest_major_action": "Senate amendment submitted"}, {"amendment_number": "S.AMDT.4036", "slug": "samdt4036", "sponsor_title": "Sen.", "sponsor": "Tom Coburn", "sponsor_id": "C000560", "sponsor_uri": "https://api.propublica.org/congress/v1/members/C000560.json", "sponsor_party": "R", "sponsor_state": "OK", "introduced_date": "2014-12-10", "title": "", "congressdotgov_url": "https://www.congress.gov/amendment/113th-congress/senate-amendment/4036/text", "latest_major_action_date": "2014-12-10", "latest_major_action": "Senate amendment submitted"}, {"amendment_number": "S.AMDT.4037", "slug": "samdt4037", "sponsor_title": "Sen.", "sponsor": "Tom Coburn", "sponsor_id": "C000560", "sponsor_uri": "https://api.propublica.org/congress/v1/members/C000560.json", "sponsor_party": "R", "sponsor_state": "OK", "introduced_date": "2014-12-10", "title": "", "congressdotgov_url": "https://www.congress.gov/amendment/113th-congress/senate-amendment/4037/text", "latest_major_action_date": "2014-12-10", "latest_major_action": "Senate amendment submitted"}, {"amendment_number": "S.AMDT.4038", "slug": "samdt4038", "sponsor_title": "Sen.", "sponsor": "Tom Coburn", "sponsor_id": "C000560", "sponsor_uri": "https://api.propublica.org/congress/v1/members/C000560.json", "sponsor_party": "R", "sponsor_state": "OK", "introduced_date": "2014-12-10", "title": "", "congressdotgov_url": "https://www.congress.gov/amendment/113th-congress/senate-amendment/4038/text", "latest_major_action_date": "2014-12-10", "latest_major_action": "Senate amendment submitted"}, {"amendment_number": "S.AMDT.4039", "slug": "samdt4039", "sponsor_title": "Sen.", "sponsor": "Tom Coburn", "sponsor_id": "C000560", "sponsor_uri": "https://api.propublica.org/congress/v1/members/C000560.json", "sponsor_party": "R", "sponsor_state": "OK", "introduced_date": "2014-12-10", "title": "", "congressdotgov_url": "https://www.congress.gov/amendment/113th-congress/senate-amendment/4039/text", "latest_major_action_date": "2014-12-10", "latest_major_action": "Senate amendment submitted"}, {"amendment_number": "S.AMDT.4040", "slug": "samdt4040", "sponsor_title": "Sen.", "sponsor": "Tom Coburn", "sponsor_id": "C000560", "sponsor_uri": "https://api.propublica.org/congress/v1/members/C000560.json", "sponsor_party": "R", "sponsor_state": "OK", "introduced_date": "2014-12-10", "title": "", "congressdotgov_url": "https://www.congress.gov/amendment/113th-congress/senate-amendment/4040/text", "latest_major_action_date": "2014-12-10", "latest_major_action": "Senate amendment submitted"}, {"amendment_number": "S.AMDT.4041", "slug": "samdt4041", "sponsor_title": "Sen.", "sponsor": "Tom Coburn", "sponsor_id": "C000560", "sponsor_uri": "https://api.propublica.org/congress/v1/members/C000560.json", "sponsor_party": "R", "sponsor_state": "OK", "introduced_date": "2014-12-10", "title": "", "congressdotgov_url": "https://www.congress.gov/amendment/113th-congress/senate-amendment/4041/text", "latest_major_action_date": "2014-12-10", "latest_major_action": "Senate amendment submitted"}, {"amendment_number": "S.AMDT.4042", "slug": "samdt4042", "sponsor_title": "Sen.", "sponsor": "Tom Coburn", "sponsor_id": "C000560", "sponsor_uri": "https://api.propublica.org/congress/v1/members/C000560.json", "sponsor_party": "R", "sponsor_state": "OK", "introduced_date": "2014-12-10", "title": "", "congressdotgov_url": "https://www.congress.gov/amendment/113th-congress/senate-amendment/4042/text", "latest_major_action_date": "2014-12-10", "latest_major_action": "Senate amendment submitted"}, {"amendment_number": "S.AMDT.4043", "slug": "samdt4043", "sponsor_title": "Sen.", "sponsor": "Tom Coburn", "sponsor_id": "C000560", "sponsor_uri": "https://api.propublica.org/congress/v1/members/C000560.json", "sponsor_party": "R", "sponsor_state": "OK", "introduced_date": "2014-12-10", "title": "", "congressdotgov_url": "https://www.congress.gov/amendment/113th-congress/senate-amendment/4043/text", "latest_major_action_date": "2014-12-10", "latest_major_action": "Senate amendment submitted"}, {"amendment_number": "S.AMDT.4044", "slug": "samdt4044", "sponsor_title": "Sen.", "sponsor": "Tom Coburn", "sponsor_id": "C000560", "sponsor_uri": "https://api.propublica.org/congress/v1/members/C000560.json", "sponsor_party": "R", "sponsor_state": "OK", "introduced_date": "2014-12-10", "title": "", "congressdotgov_url": "https://www.congress.gov/amendment/113th-congress/senate-amendment/4044/text", "latest_major_action_date": "2014-12-10", "latest_major_action": "Senate amendment submitted"}, {"amendment_number": "S.AMDT.4045", "slug": "samdt4045", "sponsor_title": "Sen.", "sponsor": "Tom Coburn", "sponsor_id": "C000560", "sponsor_uri": "https://api.propublica.org/congress/v1/members/C000560.json", "sponsor_party": "R", "sponsor_state": "OK", "introduced_date": "2014-12-10", "title": "", "congressdotgov_url": "https://www.congress.gov/amendment/113th-congress/senate-amendment/4045/text", "latest_major_action_date": "2014-12-10", "latest_major_action": "Senate amendment submitted"}, {"amendment_number": "S.AMDT.4046", "slug": "samdt4046", "sponsor_title": "Sen.", "sponsor": "Tom Coburn", "sponsor_id": "C000560", "sponsor_uri": "https://api.propublica.org/congress/v1/members/C000560.json", "sponsor_party": "R", "sponsor_state": "OK", "introduced_date": "2014-12-10", "title": "", "congressdotgov_url": "https://www.congress.gov/amendment/113th-congress/senate-amendment/4046/text", "latest_major_action_date": "2014-12-10", "latest_major_action": "Senate amendment submitted"}, {"amendment_number": "S.AMDT.4047", "slug": "samdt4047", "sponsor_title": "Sen.", "sponsor": "Tom Coburn", "sponsor_id": "C000560", "sponsor_uri": "https://api.propublica.org/congress/v1/members/C000560.json", "sponsor_party": "R", "sponsor_state": "OK", "introduced_date": "2014-12-10", "title": "", "congressdotgov_url": "https://www.congress.gov/amendment/113th-congress/senate-amendment/4047/text", "latest_major_action_date": "2014-12-10", "latest_major_action": "Senate amendment submitted"}, {"amendment_number": "S.AMDT.4048", "slug": "samdt4048", "sponsor_title": "Sen.", "sponsor": "Tom Coburn", "sponsor_id": "C000560", "sponsor_uri": "https://api.propublica.org/congress/v1/members/C000560.json", "sponsor_party": "R", "sponsor_state": "OK", "introduced_date": "2014-12-10", "title": "", "congressdotgov_url": "https://www.congress.gov/amendment/113th-congress/senate-amendment/4048/text", "latest_major_action_date": "2014-12-10", "latest_major_action": "Senate amendment submitted"}, {"amendment_number": "S.AMDT.4049", "slug": "samdt4049", "sponsor_title": "Sen.", "sponsor": "Tom Coburn", "sponsor_id": "C000560", "sponsor_uri": "https://api.propublica.org/congress/v1/members/C000560.json", "sponsor_party": "R", "sponsor_state": "OK", "introduced_date": "2014-12-10", "title": "", "congressdotgov_url": "https://www.congress.gov/amendment/113th-congress/senate-amendment/4049/text", "latest_major_action_date": "2014-12-10", "latest_major_action": "Senate amendment submitted"}, {"amendment_number": "S.AMDT.4050", "slug": "samdt4050", "sponsor_title": "Sen.", "sponsor": "Tom Coburn", "sponsor_id": "C000560", "sponsor_uri": "https://api.propublica.org/congress/v1/members/C000560.json", "sponsor_party": "R", "sponsor_state": "OK", "introduced_date": "2014-12-10", "title": "", "congressdotgov_url": "https://www.congress.gov/amendment/113th-congress/senate-amendment/4050/text", "latest_major_action_date": "2014-12-10", "latest_major_action": "Senate amendment submitted"}, {"amendment_number": "S.AMDT.4051", "slug": "samdt4051", "sponsor_title": "Sen.", "sponsor": "Tom Coburn", "sponsor_id": "C000560", "sponsor_uri": "https://api.propublica.org/congress/v1/members/C000560.json", "sponsor_party": "R", "sponsor_state": "OK", "introduced_date": "2014-12-10", "title": "", "congressdotgov_url": "https://www.congress.gov/amendment/113th-congress/senate-amendment/4051/text", "latest_major_action_date": "2014-12-10", "latest_major_action": "Senate amendment submitted"}]}