{"congress": "114", "bill_id": "hr4038-114", "num_results": 7, "offset": 0, "amendments": [{"amendment_number": "S.Amdt.2951", "slug": "samdt2951", "sponsor_title": "Sen.", "sponsor": "Jeff Flake", "sponsor_id": "F000444", "sponsor_uri": "https://api.propublica.org/congress/v1/members/F000444.json", "sponsor_party": "R", "sponsor_state": "AZ", "introduced_date": "2016-01-20", "title": "", "congressdotgov_url": "https://www.congress.gov/amendment/114th-congress/senate-amendment/2951/text", "latest_major_action_date": "2016-01-20", "latest_major_action": "Senate amendment submitted"}, {"amendment_number": "S.Amdt.2950", "slug": "samdt2950", "sponsor_title": "Sen.", "sponsor": "Jeff Flake", "sponsor_id": "F000444", "sponsor_uri": "https://api.propublica.org/congress/v1/members/F000444.json", "sponsor_party": "R", "sponsor_state": "AZ", "introduced_date": "2016-01-20", "title": "", "congressdotgov_url": "https://www.congress.gov/amendment/114th-congress/senate-amendment/2950/text", "latest_major_action_date": "2016-01-20", "latest_major_action": "Senate amendment submitted"}, {"amendment_number": "S.Amdt.2949", "slug": "samdt2949", "sponsor_title": "Sen.", "sponsor": "Mark Steven Kirk", "sponsor_id": "K000360", "sponsor_uri": "https://api.propublica.org/congress/v1/members/K000360.json", "sponsor_party": "R", "sponsor_state": "IL", "introduced_date": "2016-01-20", "title": "", "congressdotgov_url": "https://www.congress.gov/amendment/114th-congress/senate-amendment/2949/text", "latest_major_action_date": "2016-01-20", "latest_major_action": "Senate amendment submitted"}, {"amendment_number": "S.Amdt.2948", "slug": "samdt2948", "sponsor_title": "Sen.", "sponsor": "Mark Steven Kirk", "sponsor_id": "K000360", "sponsor_uri": "https://api.propublica.org/congress/v1/members/K000360.json", "sponsor_party": "R", "sponsor_state": "IL", "introduced_date": "2016-01-20", "title": "", "congressdotgov_url": "https://www.congress.gov/amendment/114th-congress/senate-amendment/2948/text", "latest_major_action_date": "2016-01-20", "latest_major_action": "Senate amendment submitted"}, {"amendment_number": "S.Amdt.2947", "slug": "samdt2947", "sponsor_title": "Sen.", "sponsor": "Mark Steven Kirk", "sponsor_id": "K000360", "sponsor_uri": "https://api.propublica.org/congress/v1/members/K000360.json", "sponsor_party": "R", "sponsor_state": "IL", "introduced_date": "2016-01-20", "title": "", "congressdotgov_url": "https://www.congress.gov/amendment/114th-congress/senate-amendment/2947/text", "latest_major_action_date": "2016-01-20", "latest_major_action": "Senate amendment submitted"}, {"amendment_number": "S.Amdt.2946", "slug": "samdt2946", "sponsor_title": "Sen.", "sponsor": "John Thune", "sponsor_id": "T000250", "sponsor_uri": "https://api.propublica.org/congress/v1/members/T000250.json", "sponsor_party": "R", "sponsor_state": "SD", "introduced_date": "2016-01-20", "title": "", "congressdotgov_url": "https://www.congress.gov/amendment/114th-congress/senate-amendment/2946/text", "latest_major_action_date": "2016-01-20", "latest_major_action": "Senate amendment submitted"}, {"amendment_number": "S.Amdt.2945", "slug": "samdt2945", "sponsor_title": "Sen.", "sponsor": "John Thune", "sponsor_id": "T000250", "sponsor_uri": "https://api.propublica.org/congress/v1/members/T000250.json", "sponsor_party": "R", "sponsor_state": "SD", "introduced_date": "2016-01-20", "title": "", "congressdotgov_url": "https://www.congress.gov/amendment/114th-congress/senate-amendment/2945/text", "latest_major_action_date": "2016-01-20", "latest_major_action": "Senate amendment submitted"}]}