{"congress": "113", "bill_id": "hr4660-113", "num_results": 20, "offset": 0, "amendments": [{"amendment_number": "S.AMDT.3260", "slug": "samdt3260", "sponsor_title": "Sen.", "sponsor": "Lamar Alexander", "sponsor_id": "A000360", "sponsor_uri": "https://api.propublica.org/congress/v1/members/A000360.json", "sponsor_party": "R", "sponsor_state": "TN", "introduced_date": "2014-06-18", "title": "", "congressdotgov_url": "https://www.congress.gov/amendment/113th-congress/senate-amendment/3260/text", "latest_major_action_date": "2014-06-18", "latest_major_action": "Senate amendment submitted"}, {"amendment_number": "S.AMDT.3261", "slug": "samdt3261", "sponsor_title": "Sen.", "sponsor": "Richard Blumenthal", "sponsor_id": "B001277", "sponsor_uri": "https://api.propublica.org/congress/v1/members/B001277.json", "sponsor_party": "D", "sponsor_state": "CT", "introduced_date": "2014-06-18", "title": "", "congressdotgov_url": "https://www.congress.gov/amendment/113th-congress/senate-amendment/3261/text", "latest_major_action_date": "2014-06-18", "latest_major_action": "Senate amendment submitted"}, {"amendment_number": "S.AMDT.3262", "slug": "samdt3262", "sponsor_title": "Sen.", "sponsor": "Amy Klobuchar", "sponsor_id": "K000367", "sponsor_uri": "https://api.propublica.org/congress/v1/members/K000367.json", "sponsor_party": "D", "sponsor_state": "MN", "introduced_date": "2014-06-18", "title": "", "congressdotgov_url": "https://www.congress.gov/amendment/113th-congress/senate-amendment/3262/text", "latest_major_action_date": "2014-06-18", "latest_major_action": "Senate amendment submitted"}, {"amendment_number": "S.AMDT.3263", "slug": "samdt3263", "sponsor_title": "Sen.", "sponsor": "John McCain", "sponsor_id": "M000303", "sponsor_uri": "https://api.propublica.org/congress/v1/members/M000303.json", "sponsor_party": "R", "sponsor_state": "AZ", "introduced_date": "2014-06-18", "title": "", "congressdotgov_url": "https://www.congress.gov/amendment/113th-congress/senate-amendment/3263/text", "latest_major_action_date": "2014-06-18", "latest_major_action": "Senate amendment submitted"}, {"amendment_number": "S.AMDT.3264", "slug": "samdt3264", "sponsor_title": "Sen.", "sponsor": "John Thune", "sponsor_id": "T000250", "sponsor_uri": "https://api.propublica.org/congress/v1/members/T000250.json", "sponsor_party": "R", "sponsor_state": "SD", "introduced_date": "2014-06-18", "title": "", "congressdotgov_url": "https://www.congress.gov/amendment/113th-congress/senate-amendment/3264/text", "latest_major_action_date": "2014-06-18", "latest_major_action": "Senate amendment submitted"}, {"amendment_number": "S.AMDT.3265", "slug": "samdt3265", "sponsor_title": "Sen.", "sponsor": "Jeanne Shaheen", "sponsor_id": "S001181", "sponsor_uri": "https://api.propublica.org/congress/v1/members/S001181.json", "sponsor_party": "D", "sponsor_state": "NH", "introduced_date": "2014-06-18", "title": "", "congressdotgov_url": "https://www.congress.gov/amendment/113th-congress/senate-amendment/3265/text", "latest_major_action_date": "2014-06-18", "latest_major_action": "Senate amendment submitted"}, {"amendment_number": "S.AMDT.3266", "slug": "samdt3266", "sponsor_title": "Sen.", "sponsor": "Lindsey Graham", "sponsor_id": "G000359", "sponsor_uri": "https://api.propublica.org/congress/v1/members/G000359.json", "sponsor_party": "R", "sponsor_state": "SC", "introduced_date": "2014-06-18", "title": "", "congressdotgov_url": "https://www.congress.gov/amendment/113th-congress/senate-amendment/3266/text", "latest_major_action_date": "2014-06-18", "latest_major_action": "Senate amendment submitted"}, {"amendment_number": "S.AMDT.3267", "slug": "samdt3267", "sponsor_title": "Sen.", "sponsor": "John Thune", "sponsor_id": "T000250", "sponsor_uri": "https://api.propublica.org/congress/v1/members/T000250.json", "sponsor_party": "R", "sponsor_state": "SD", "introduced_date": "2014-06-18", "title": "", "congressdotgov_url": "https://www.congress.gov/amendment/113th-congress/senate-amendment/3267/text", "latest_major_action_date": "2014-06-18", "latest_major_action": "Senate amendment submitted"}, {"amendment_number": "S.AMDT.3268", "slug": "samdt3268", "sponsor_title": "Sen.", "sponsor": "Tammy Baldwin", "sponsor_id": "B001230", "sponsor_uri": "https://api.propublica.org/congress/v1/members/B001230.json", "sponsor_party": "D", "sponsor_state": "WI", "introduced_date": "2014-06-18", "title": "", "congressdotgov_url": "https://www.congress.gov/amendment/113th-congress/senate-amendment/3268/text", "latest_major_action_date": "2014-06-18", "latest_major_action": "Senate amendment submitted"}, {"amendment_number": "S.AMDT.3269", "slug": "samdt3269", "sponsor_title": "Sen.", "sponsor": "Dean Heller", "sponsor_id": "H001041", "sponsor_uri": "https://api.propublica.org/congress/v1/members/H001041.json", "sponsor_party": "R", "sponsor_state": "NV", "introduced_date": "2014-06-18", "title": "", "congressdotgov_url": "https://www.congress.gov/amendment/113th-congress/senate-amendment/3269/text", "latest_major_action_date": "2014-06-18", "latest_major_action": "Senate amendment submitted"}, {"amendment_number": "H.AMDT.690", "slug": "hamdt690", "sponsor_title": "Rep.", "sponsor": "Stephen F. Lynch", "sponsor_id": "L000562", "sponsor_uri": "https://api.propublica.org/congress/v1/members/L000562.json", "sponsor_party": "D", "sponsor_state": "MA", "introduced_date": "2014-05-28", "title": "An amendment to reduce the funding for operations and administration in the International Trade Administration by $3 million and to increase funding for State and local law enforcement assistance (drug courts) by a similar amount.", "congressdotgov_url": "https://www.congress.gov/amendment/113th-congress/house-amendment/690/text", "latest_major_action_date": "2014-05-28", "latest_major_action": "On agreeing to the Lynch amendment (A001) Agreed to by voice vote."}, {"amendment_number": "S.AMDT.3270", "slug": "samdt3270", "sponsor_title": "Sen.", "sponsor": "Dean Heller", "sponsor_id": "H001041", "sponsor_uri": "https://api.propublica.org/congress/v1/members/H001041.json", "sponsor_party": "R", "sponsor_state": "NV", "introduced_date": "2014-06-18", "title": "", "congressdotgov_url": "https://www.congress.gov/amendment/113th-congress/senate-amendment/3270/text", "latest_major_action_date": "2014-06-18", "latest_major_action": "Senate amendment submitted"}, {"amendment_number": "H.AMDT.691", "slug": "hamdt691", "sponsor_title": "Rep.", "sponsor": "Susan A. Davis", "sponsor_id": "D000598", "sponsor_uri": "https://api.propublica.org/congress/v1/members/D000598.json", "sponsor_party": "D", "sponsor_state": "CA", "introduced_date": "2014-05-28", "title": "An amendment to increase the funding for operations and administration in the International Trade Administration by $3 million and to reduce funding for salaries and expenses of the Federal Prison System by a similar amount.", "congressdotgov_url": "https://www.congress.gov/amendment/113th-congress/house-amendment/691/text", "latest_major_action_date": "2014-05-28", "latest_major_action": "On agreeing to the Davis (CA) amendment (A002) Failed by voice vote."}, {"amendment_number": "S.AMDT.3271", "slug": "samdt3271", "sponsor_title": "Sen.", "sponsor": "Deb Fischer", "sponsor_id": "F000463", "sponsor_uri": "https://api.propublica.org/congress/v1/members/F000463.json", "sponsor_party": "R", "sponsor_state": "NE", "introduced_date": "2014-06-18", "title": "", "congressdotgov_url": "https://www.congress.gov/amendment/113th-congress/senate-amendment/3271/text", "latest_major_action_date": "2014-06-18", "latest_major_action": "Senate amendment submitted"}, {"amendment_number": "H.AMDT.692", "slug": "hamdt692", "sponsor_title": "Rep.", "sponsor": "Dave Reichert", "sponsor_id": "R000578", "sponsor_uri": "https://api.propublica.org/congress/v1/members/R000578.json", "sponsor_party": "R", "sponsor_state": "WA", "introduced_date": "2014-05-28", "title": "An amendment to reduce funding for periodic census and programs by $110 million and to increase funding for community oriented policing services programs (hiring and rehiring of additional career law enforcement officers) by a similar amount.", "congressdotgov_url": "https://www.congress.gov/amendment/113th-congress/house-amendment/692/text", "latest_major_action_date": "2014-05-28", "latest_major_action": "On agreeing to the Reichert amendment (A003) Agreed to by voice vote."}, {"amendment_number": "S.AMDT.3272", "slug": "samdt3272", "sponsor_title": "Sen.", "sponsor": "Deb Fischer", "sponsor_id": "F000463", "sponsor_uri": "https://api.propublica.org/congress/v1/members/F000463.json", "sponsor_party": "R", "sponsor_state": "NE", "introduced_date": "2014-06-18", "title": "", "congressdotgov_url": "https://www.congress.gov/amendment/113th-congress/senate-amendment/3272/text", "latest_major_action_date": "2014-06-18", "latest_major_action": "Senate amendment submitted"}, {"amendment_number": "H.AMDT.693", "slug": "hamdt693", "sponsor_title": "Rep.", "sponsor": "Dan Kildee", "sponsor_id": "K000380", "sponsor_uri": "https://api.propublica.org/congress/v1/members/K000380.json", "sponsor_party": "D", "sponsor_state": "MI", "introduced_date": "2014-05-28", "title": "An amendment to increase funding for operations and administration in the International Trade Administration by $8 million and to reduce funding for NASA exploration by $10 million.", "congressdotgov_url": "https://www.congress.gov/amendment/113th-congress/house-amendment/693/text", "latest_major_action_date": "2014-05-28", "latest_major_action": "On agreeing to the Kildee amendment (A004) Failed by voice vote."}, {"amendment_number": "S.AMDT.3273", "slug": "samdt3273", "sponsor_title": "Sen.", "sponsor": "James M. Inhofe", "sponsor_id": "I000024", "sponsor_uri": "https://api.propublica.org/congress/v1/members/I000024.json", "sponsor_party": "R", "sponsor_state": "OK", "introduced_date": "2014-06-18", "title": "", "congressdotgov_url": "https://www.congress.gov/amendment/113th-congress/senate-amendment/3273/text", "latest_major_action_date": "2014-06-18", "latest_major_action": "Senate amendment submitted"}, {"amendment_number": "H.AMDT.694", "slug": "hamdt694", "sponsor_title": "Rep.", "sponsor": "Jim Langevin", "sponsor_id": "L000559", "sponsor_uri": "https://api.propublica.org/congress/v1/members/L000559.json", "sponsor_party": "D", "sponsor_state": "RI", "introduced_date": "2014-05-28", "title": "An amendment to designate $5 million for a survey on the NIST cybersecurity framework for reducing cyber risks to critical infrastructure.", "congressdotgov_url": "https://www.congress.gov/amendment/113th-congress/house-amendment/694/text", "latest_major_action_date": "2014-05-28", "latest_major_action": "On agreeing to the Langevin amendment Agreed to by voice vote."}, {"amendment_number": "S.AMDT.3274", "slug": "samdt3274", "sponsor_title": "Sen.", "sponsor": "James M. Inhofe", "sponsor_id": "I000024", "sponsor_uri": "https://api.propublica.org/congress/v1/members/I000024.json", "sponsor_party": "R", "sponsor_state": "OK", "introduced_date": "2014-06-18", "title": "", "congressdotgov_url": "https://www.congress.gov/amendment/113th-congress/senate-amendment/3274/text", "latest_major_action_date": "2014-06-18", "latest_major_action": "Senate amendment submitted"}]}