{"congress": "113", "bill_id": "s2432-113", "bill_slug": "s2432", "bill_type": "s", "number": "S.2432", "bill_uri": "https://api.propublica.org/congress/v1/113/bills/s2432.json", "url_number": "s2432", "title": "A bill to amend the Higher Education Act of 1965 to provide for the refinancing of certain Federal student loans, and for other purposes.", "sponsor_title": "Sen.", "sponsor_id": "W000817", "sponsor_name": "Elizabeth Warren", "sponsor_state": "MA", "sponsor_party": "D", "sponsor_uri": "https://api.propublica.org/congress/v1/members/W000817.json", "introduced_date": "2014-06-04", "number_of_cosponsors": 44, "committees": "Senate Banking, Housing, and Urban Affairs Committee", "latest_major_action_date": "2014-09-18", "latest_major_action": "Motion to proceed to consideration of measure made in Senate. (consideration: CR S5725-5726)", "house_passage_vote": null, "senate_passage_vote": null, "subjects": [{"name": "Education", "url_name": "education"}, {"name": "Higher education", "url_name": "higher-education"}, {"name": "Budget deficits and national debt", "url_name": "budget-deficits-and-national-debt"}, {"name": "Student aid and college costs", "url_name": "student-aid-and-college-costs"}, {"name": "Income tax deductions", "url_name": "income-tax-deductions"}, {"name": "Income tax rates", "url_name": "income-tax-rates"}, {"name": "Social work, volunteer service, charitable organizations", "url_name": "social-work-volunteer-service-charitable-organizations"}, {"name": "Government lending and loan guarantees", "url_name": "government-lending-and-loan-guarantees"}, {"name": "Interest, dividends, interest rates", "url_name": "interest-dividends-interest-rates"}, {"name": "User charges and fees", "url_name": "user-charges-and-fees"}, {"name": "Inflation and prices", "url_name": "inflation-and-prices"}, {"name": "Education", "url_name": "education"}]}