{"congress": "113", "bill_id": "s540-113", "bill_slug": "s540", "bill_type": "s", "number": "S.540", "bill_uri": "https://api.propublica.org/congress/v1/113/bills/s540.json", "url_number": "s540", "title": "A bill to designate the air route traffic control center located in Nashua, New Hampshire, as the 'Patricia Clark Boston Air Route Traffic Control Center'.", "sponsor_title": "Sen.", "sponsor_id": "S001181", "sponsor_name": "Jeanne Shaheen", "sponsor_state": "NH", "sponsor_party": "D", "sponsor_uri": "https://api.propublica.org/congress/v1/members/S001181.json", "introduced_date": "2013-03-12", "number_of_cosponsors": 1, "committees": "House Transportation and Infrastructure Committee", "latest_major_action_date": "2014-02-15", "latest_major_action": "Became Public Law No: 113-83.", "house_passage_vote": "2014-02-11", "senate_passage_vote": "2013-03-21", "subjects": [{"name": "Congressional tributes", "url_name": "congressional-tributes"}, {"name": "New Hampshire", "url_name": "new-hampshire"}, {"name": "Government buildings, facilities, and property", "url_name": "government-buildings-facilities-and-property"}, {"name": "Economics and public finance", "url_name": "economics-and-public-finance"}, {"name": "Budget deficits and national debt", "url_name": "budget-deficits-and-national-debt"}, {"name": "Transportation and public works", "url_name": "transportation-and-public-works"}, {"name": "Aviation and airports", "url_name": "aviation-and-airports"}, {"name": "Economics and Public Finance", "url_name": "economics-and-public-finance"}]}