{"congress": "113", "bill_id": "hr2642-113", "bill_slug": "hr2642", "bill_type": "hr", "number": "H.R.2642", "bill_uri": "https://api.propublica.org/congress/v1/113/bills/hr2642.json", "url_number": "hr2642", "title": "To provide for the reform and continuation of agricultural and other programs of the Department of Agriculture through fiscal year 2018, and for other purposes.", "sponsor_title": "Rep.", "sponsor_id": "L000491", "sponsor_name": "Frank D. Lucas", "sponsor_state": "OK", "sponsor_party": "R", "sponsor_uri": "https://api.propublica.org/congress/v1/members/L000491.json", "introduced_date": "2013-07-10", "number_of_cosponsors": 0, "committees": "House Agriculture Committee", "latest_major_action_date": "2014-02-07", "latest_major_action": "Became Public Law No: 113-79.", "house_passage_vote": "2013-10-12", "senate_passage_vote": "2013-07-18", "subjects": [{"name": "Federal officials", "url_name": "federal-officials"}, {"name": "Congressional oversight", "url_name": "congressional-oversight"}, {"name": "Higher education", "url_name": "higher-education"}, {"name": "Watersheds", "url_name": "watersheds"}, {"name": "Economic development", "url_name": "economic-development"}, {"name": "Canada", "url_name": "canada"}, {"name": "Research and development", "url_name": "research-and-development"}, {"name": "Virginia", "url_name": "virginia"}, {"name": "Administrative remedies", "url_name": "administrative-remedies"}, {"name": "Land transfers", "url_name": "land-transfers"}, {"name": "Small business", "url_name": "small-business"}, {"name": "Texas", "url_name": "texas"}, {"name": "Cemeteries and funerals", "url_name": "cemeteries-and-funerals"}, {"name": "Birds", "url_name": "birds"}, {"name": "Medical research", "url_name": "medical-research"}, {"name": "Department of Agriculture", "url_name": "department-of-agriculture"}, {"name": "Fires", "url_name": "fires"}, {"name": "Fishes", "url_name": "fishes"}, {"name": "Great Lakes", "url_name": "great-lakes"}, {"name": "Meat", "url_name": "meat"}]}