{"congress": "113", "bill_id": "s743-113", "bill_slug": "s743", "bill_type": "s", "number": "S.743", "bill_uri": "https://api.propublica.org/congress/v1/113/bills/s743.json", "url_number": "s743", "title": "A bill to restore States' sovereign rights to enforce State and local sales and use tax laws, and for other purposes.", "sponsor_title": "Sen.", "sponsor_id": "E000285", "sponsor_name": "Michael B. Enzi", "sponsor_state": "WY", "sponsor_party": "R", "sponsor_uri": "https://api.propublica.org/congress/v1/members/E000285.json", "introduced_date": "2013-04-16", "number_of_cosponsors": 29, "committees": "House Judiciary Committee", "latest_major_action_date": "2013-06-14", "latest_major_action": "Referred to the Subcommittee on Regulatory Reform, Commercial And Antitrust Law.", "house_passage_vote": null, "senate_passage_vote": "2013-05-06", "subjects": [{"name": "Taxation", "url_name": "taxation"}, {"name": "Sales and excise taxes", "url_name": "sales-and-excise-taxes"}, {"name": "State and local taxation", "url_name": "state-and-local-taxation"}, {"name": "State and local government operations", "url_name": "state-and-local-government-operations"}, {"name": "Tax administration and collection, taxpayers", "url_name": "tax-administration-and-collection-taxpayers"}, {"name": "Internet and video services", "url_name": "internet-and-video-services"}, {"name": "Retail and wholesale trades", "url_name": "retail-and-wholesale-trades"}, {"name": "Taxation", "url_name": "taxation"}]}