{"congress": "116", "bill_id": "sjres20-116", "bill_slug": "sjres20", "bill_type": "sjres", "number": "S.J.RES.20", "bill_uri": "https://api.propublica.org/congress/v1/116/bills/sjres20.json", "url_number": "sjres20", "title": "A joint resolution relating to the disapproval of the proposed sale to the Government of Bahrain of certain defense articles and services.", "sponsor_title": "Sen.", "sponsor_id": "P000603", "sponsor_name": "Rand Paul", "sponsor_state": "KY", "sponsor_party": "R", "sponsor_uri": "https://api.propublica.org/congress/v1/members/P000603.json", "introduced_date": "2019-05-13", "number_of_cosponsors": 0, "committees": "Senate Foreign Relations Committee", "latest_major_action_date": "2019-06-13", "latest_major_action": "Motion to discharge Senate Committee on Foreign Relations rejected by Yea-Nay Vote. 43 - 56. Record Vote Number: 161. (consideration: CR S3461-3462)", "house_passage_vote": null, "senate_passage_vote": null, "subjects": [{"name": "Congressional oversight", "url_name": "congressional-oversight"}, {"name": "Bahrain", "url_name": "bahrain"}, {"name": "Middle East", "url_name": "middle-east"}, {"name": "Military assistance, sales, and agreements", "url_name": "military-assistance-sales-and-agreements"}, {"name": "International Affairs", "url_name": "international-affairs"}]}