[{"@attributes": {"industry_code": "F07", "industry_name": "Securities & Investment", "indivs": "3128236", "pacs": "251200", "total": "3379436"}}, {"@attributes": {"industry_code": "K01", "industry_name": "Lawyers/Law Firms", "indivs": "1784504", "pacs": "255551", "total": "2040055"}}, {"@attributes": {"industry_code": "F10", "industry_name": "Real Estate", "indivs": "1861971", "pacs": "90500", "total": "1952471"}}, {"@attributes": {"industry_code": "F09", "industry_name": "Insurance", "indivs": "388613", "pacs": "367000", "total": "755613"}}, {"@attributes": {"industry_code": "K02", "industry_name": "Lobbyists", "indivs": "702777", "pacs": "19900", "total": "722677"}}, {"@attributes": {"industry_code": "H01", "industry_name": "Health Professionals", "indivs": "364190", "pacs": "266500", "total": "630690"}}, {"@attributes": {"industry_code": "B02", "industry_name": "TV/Movies/Music", "indivs": "468460", "pacs": "84500", "total": "552960"}}, {"@attributes": {"industry_code": "B12", "industry_name": "Electronics Mfg & Equip", "indivs": "418041", "pacs": "125534", "total": "543575"}}, {"@attributes": {"industry_code": "F13", "industry_name": "Misc Finance", "indivs": "467317", "pacs": "66600", "total": "533917"}}, {"@attributes": {"industry_code": "W06", "industry_name": "Retired", "indivs": "515547", "pacs": "0", "total": "515547"}}]