[{"@attributes": {"industry_code": "W06", "industry_name": "Retired", "indivs": "551567", "pacs": "0", "total": "551567"}}, {"@attributes": {"industry_code": "Q02", "industry_name": "Democratic/Liberal", "indivs": "207135", "pacs": "11070", "total": "218205"}}, {"@attributes": {"industry_code": "K01", "industry_name": "Lawyers/Law Firms", "indivs": "114319", "pacs": "13000", "total": "127319"}}, {"@attributes": {"industry_code": "P04", "industry_name": "Public Sector Unions", "indivs": "600", "pacs": "119500", "total": "120100"}}, {"@attributes": {"industry_code": "H01", "industry_name": "Health Professionals", "indivs": "64887", "pacs": "50000", "total": "114887"}}, {"@attributes": {"industry_code": "W04", "industry_name": "Education", "indivs": "80205", "pacs": "0", "total": "80205"}}, {"@attributes": {"industry_code": "Q03", "industry_name": "Leadership PACs", "indivs": "0", "pacs": "71500", "total": "71500"}}, {"@attributes": {"industry_code": "P05", "industry_name": "Misc Unions", "indivs": "3750", "pacs": "50000", "total": "53750"}}, {"@attributes": {"industry_code": "Q11", "industry_name": "Environment", "indivs": "48890", "pacs": "3257", "total": "52147"}}, {"@attributes": {"industry_code": "B02", "industry_name": "TV/Movies/Music", "indivs": "46100", "pacs": "0", "total": "46100"}}]